{
  "navigation": {
    "home": "Home",
    "about": "About"
  },
  "page": {
    "home": {
      "heroSection": {
        "title": "Report Incident",
        "description": "Click here to go to the report form to report something queer-hostile",
        "buttonText": "Report Incident"
      }
    },
    "melden": {
      "stepper": {
        "firstStep": "General information",
        "secondStep": "Information on the incident",
        "thirdStep": "Send enquiry"
      },
      "formFields": {},
      "button": {
        "next": "Los geht's",
        "prev": "Back",
        "submit": "Send"
      }
    },
    "about": {
      "title": "About Us",
      "description": "This is the about page"
    },
    "footer": {
      "datenschutz": "Data protection"
    }
  }
}
